grump/__init__.py
grump/grump.py
tests/__init__.py
tests/test_grump.py
grump-0.0.12.dist-info/LICENSE
grump-0.0.12.dist-info/METADATA
grump-0.0.12.dist-info/WHEEL
grump-0.0.12.dist-info/entry_points.txt
grump-0.0.12.dist-info/top_level.txt
grump-0.0.12.dist-info/RECORD
