Metadata-Version: 2.1
Name: grump
Version: 0.0.12
Summary: Grep for Unstructured Multiline Paragraphs
Home-page: https://github.com/andrewsolomon/grump
Author: Andrew Solomon
Author-email: andrew@geekuni.com
License: UNKNOWN
Platform: UNKNOWN
Classifier: Programming Language :: Python :: 3
Classifier: License :: OSI Approved :: Apache Software License
Classifier: Operating System :: OS Independent
Classifier: Development Status :: 3 - Alpha
Classifier: Intended Audience :: System Administrators
Classifier: Intended Audience :: Developers
Requires-Python: >=3.8
